active_link/__init__.py
active_link/apps.py
active_link/templatetags/__init__.py
active_link/templatetags/active_link_tags.py
django_active_link-0.3.0.dist-info/METADATA
django_active_link-0.3.0.dist-info/WHEEL
django_active_link-0.3.0.dist-info/licenses/AUTHORS.rst
django_active_link-0.3.0.dist-info/licenses/LICENSE
django_active_link-0.3.0.dist-info/RECORD
