Metadata-Version: 2.4
Name: django-active-link
Version: 0.3.0
Summary: The best and simplest way to highlight active links in your Django app.
License: BSD-3-Clause
License-File: AUTHORS.rst
License-File: LICENSE
Keywords: django,active,link,django-active-link,sidebar,navbar
Author: Valery Melou
Author-email: valerymelou@gmail.com
Maintainer: Frederich Pedersen
Maintainer-email: frodo@hobbits.dk
Requires-Python: >=3.10,<4.0
Classifier: Development Status :: 3 - Alpha
Classifier: Framework :: Django
Classifier: Framework :: Django :: 4.2
Classifier: Framework :: Django :: 5.1
Classifier: Framework :: Django :: 5.2
Classifier: Intended Audience :: Developers
Classifier: License :: OSI Approved :: BSD License
Classifier: Natural Language :: English
Classifier: Programming Language :: Python :: 3
Classifier: Programming Language :: Python :: 3.10
Classifier: Programming Language :: Python :: 3.11
Classifier: Programming Language :: Python :: 3.12
Classifier: Programming Language :: Python :: 3.13
Classifier: Programming Language :: Python :: 3.14
Provides-Extra: test
Project-URL: Bug Tracker, https://github.com/valerymelou/django-active-link/issues
Project-URL: Documentation, https://django-active-link.readthedocs.io/
Project-URL: Repository, https://github.com/valerymelou/django-active-link
Project-URL: codecov, https://codecov.io/gh/valerymelou/django-active-link
